polyllm/__init__.py
polyllm/__main__.py
polyllm/demo.py
polyllm/langchain.py
polyllm/load_helpers.py
polyllm/polyllm.py
polyllm/utils.py
polyllm/providers/p_anthropic.py
polyllm/providers/p_google.py
polyllm/providers/p_litellm.py
polyllm/providers/p_llamacpppython.py
polyllm/providers/p_llamacppserver.py
polyllm/providers/p_mlx.py
polyllm/providers/p_ollama.py
polyllm/providers/p_openai.py
polyllm/providers/gbnf/GBNF.py
polyllm/providers/gbnf/__init__.py
polyllm/providers/gbnf/grammar_graph/__init__.py
polyllm/providers/gbnf/grammar_graph/colorize.py
polyllm/providers/gbnf/grammar_graph/get_input_as_code_points.py
polyllm/providers/gbnf/grammar_graph/get_parent_stack_id.py
polyllm/providers/gbnf/grammar_graph/get_serialized_rule_key.py
polyllm/providers/gbnf/grammar_graph/grammar_graph_types.py
polyllm/providers/gbnf/grammar_graph/graph.py
polyllm/providers/gbnf/grammar_graph/graph_node.py
polyllm/providers/gbnf/grammar_graph/graph_pointer.py
polyllm/providers/gbnf/grammar_graph/parse_state.py
polyllm/providers/gbnf/grammar_graph/pointers.py
polyllm/providers/gbnf/grammar_graph/print.py
polyllm/providers/gbnf/grammar_graph/rule_ref.py
polyllm/providers/gbnf/grammar_graph/type_guards.py
polyllm/providers/gbnf/grammar_parser/__init__.py
polyllm/providers/gbnf/grammar_parser/build_rule_stack.py
polyllm/providers/gbnf/rules_builder/__init__.py
polyllm/providers/gbnf/rules_builder/is_word_char.py
polyllm/providers/gbnf/rules_builder/parse_char.py
polyllm/providers/gbnf/rules_builder/parse_name.py
polyllm/providers/gbnf/rules_builder/parse_space.py
polyllm/providers/gbnf/rules_builder/rules_builder.py
polyllm/providers/gbnf/rules_builder/rules_builder_types.py
polyllm/providers/gbnf/rules_builder/symbol_ids.py
polyllm/providers/gbnf/utils/__init__.py
polyllm/providers/gbnf/utils/is_point_in_range.py
polyllm/providers/gbnf/utils/validate_non_empty.py
polyllm/providers/gbnf/utils/errors/__init__.py
polyllm/providers/gbnf/utils/errors/build_error_position.py
polyllm-1.0.6.dist-info/LICENSE
polyllm-1.0.6.dist-info/METADATA
polyllm-1.0.6.dist-info/WHEEL
polyllm-1.0.6.dist-info/top_level.txt
polyllm-1.0.6.dist-info/RECORD
