Metadata-Version: 2.2
Name: polyllm
Version: 1.0.6
Summary: A unified interface for querying multiple large language models
Author: Rory Butler
Project-URL: Homepage, https://github.com/RoryMB/polyllm
Project-URL: Bug Tracker, https://github.com/RoryMB/polyllm/issues
Classifier: Programming Language :: Python :: 3
Classifier: License :: OSI Approved :: MIT License
Classifier: Operating System :: OS Independent
Classifier: Intended Audience :: Developers
Classifier: Topic :: Scientific/Engineering :: Artificial Intelligence
Requires-Python: <3.13,>=3.10
License-File: LICENSE
Requires-Dist: anthropic
Requires-Dist: backoff
Requires-Dist: google-generativeai
Requires-Dist: litellm
Requires-Dist: llama-cpp-python
Requires-Dist: mlx-lm
Requires-Dist: ollama
Requires-Dist: openai
Requires-Dist: pydantic
